kubesync/__init__.py
kubesync/arguments.py
kubesync/colors.py
kubesync/dock.py
kubesync/kube.py
kubesync/models.py
kubesync/radar.py
kubesync/utils.py
kubesync-0.9b3.post2.dist-info/METADATA
kubesync-0.9b3.post2.dist-info/WHEEL
kubesync-0.9b3.post2.dist-info/entry_points.txt
kubesync-0.9b3.post2.dist-info/top_level.txt
kubesync-0.9b3.post2.dist-info/RECORD
