Metadata-Version: 2.1
Name: kubesync
Version: 0.9b3.post2
Summary: Kubernetes Host to Pod Synchronization Tool
Home-page: https://github.com/ahmetkotan/kubesync
Author: ahmetkotan
Author-email: ahmtkotan@gmail.com
License: UNKNOWN
Platform: UNKNOWN
Classifier: Programming Language :: Python :: 3
Classifier: License :: OSI Approved :: MIT License
Classifier: Development Status :: 4 - Beta
Classifier: Operating System :: Unix
Requires-Dist: click (>=7.1.1)
Requires-Dist: tabulate (>=0.8.7)
Requires-Dist: watchdog (>=0.10.2)
Requires-Dist: docker (>=4.2.0)
Requires-Dist: requests
Requires-Dist: kubernetes (>=11.0.0)
Requires-Dist: pyyaml (>=3.12)
Requires-Dist: python-dateutil (>=2.5.3)
Requires-Dist: google-auth (>=1.0.1)
Requires-Dist: minislite (>=0.9.1)
